LICENSE
MANIFEST.in
README.rst
nosetests
repo_manager.cfg.sample
repo_manager.spec
runtests.sh
setup.py
repo_manager/__init__.py
repo_manager/repo_manager.py
repo_manager.egg-info/PKG-INFO
repo_manager.egg-info/SOURCES.txt
repo_manager.egg-info/dependency_links.txt
repo_manager.egg-info/entry_points.txt
repo_manager.egg-info/top_level.txt
tests/__init__.py
tests/__init__.pyc
tests/repo/fedocal-0.5.0-1.el6.src.rpm
tests/repo/fedocal-0.5.1-1.el6.src.rpm
tests/repo/fedocal-0.6.0-1.el6.src.rpm
tests/repo/fedocal-0.6.1-1.el6.src.rpm
tests/repo/pkgdb2-0.5-1.el6.src.rpm
tests/repo/pkgdb2-0.6-1.el6.src.rpm
tests/repo/pkgdb2-0.7-1.el6.src.rpm
tests/repo/pkgdb2-0.8-1.el6.src.rpm