Metadata-Version: 1.0
Name: repo-manager
Version: 0.1.0
Summary: A simple application to manage RPM repositories
Home-page: https://github.com/pypingou/repo_manager
Author: Pierre-Yves Chibon
Author-email: pingou@pingoured.fr
License: GPLv3+
Platform: UNKNOWN
